m3_db_utils/__init__.py
m3_db_utils/api.py
m3_db_utils/apps.py
m3_db_utils/consts.py
m3_db_utils/decorators.py
m3_db_utils/exceptions.py
m3_db_utils/excludes.py
m3_db_utils/helpers.py
m3_db_utils/logger.py
m3_db_utils/mixins.py
m3_db_utils/models.py
m3_db_utils/options.py
m3_db_utils/receivers.py
m3_db_utils/settings.py
m3_db_utils/signals.py
m3_db_utils/strings.py
m3_db_utils/wrappers.py
m3_db_utils/migrations/__init__.py
m3_db_utils-0.8.0.dist-info/METADATA
m3_db_utils-0.8.0.dist-info/WHEEL
m3_db_utils-0.8.0.dist-info/top_level.txt
m3_db_utils-0.8.0.dist-info/RECORD
