Metadata-Version: 2.4
Name: m3-db-utils
Version: 0.8.0
Summary: Utils for working with database.
Author-email: Alexander Danilenko <a.danilenko@bars.group>
License-Expression: Apache-2.0
Project-URL: Homepage, https://stash.bars-open.ru/projects/M3/repos/m3-db-utils/browse
Project-URL: Repository, https://stash.bars-open.ru/scm/m3/m3-db-utils.git
Classifier: Development Status :: 5 - Production/Stable
Classifier: Programming Language :: Python
Classifier: Programming Language :: Python :: 3
Classifier: Programming Language :: Python :: 3.9
Classifier: Programming Language :: Python :: 3.10
Classifier: Programming Language :: Python :: 3.11
Classifier: Programming Language :: Python :: 3.12
Classifier: Intended Audience :: Developers
Classifier: Environment :: Web Environment
Requires-Python: >=3.9
Requires-Dist: Django>=1.11.29
Requires-Dist: Pygments>=2.5.2
Requires-Dist: sqlparse>=0.4.2
Requires-Dist: m3_django_compatibility<2,>=1.12.0
Provides-Extra: dev
Requires-Dist: isort==5.12.0; extra == "dev"
Requires-Dist: ruff==0.12.1; extra == "dev"
Provides-Extra: docs
Requires-Dist: sphinx<7.5,>=7; extra == "docs"
Requires-Dist: sphinx-autodoc-typehints<2.5,>=2; extra == "docs"
Requires-Dist: myst-parser<3.2,>=3; extra == "docs"
Requires-Dist: sphinx_design<0.7,>=0.6; extra == "docs"
